reslate_finesse/__init__.py
reslate_finesse/__main__.py
reslate_finesse/cleaner.py
reslate_finesse/enums.py
reslate_finesse/loader.py
reslate_finesse/object_info.py
reslate_finesse/parsing.py
reslate_finesse/version.py
reslate_finesse/writer.py
reslate_finesse/templates/__init__.py
reslate_finesse/templates/load.py
reslate_finesse/templates/templates/classes_overview.rst
reslate_finesse/templates/templates/dataclasses_overview.rst
reslate_finesse/templates/templates/enums_overview.rst
reslate_finesse/templates/templates/functions_section.rst
reslate_finesse/templates/templates/methods_section.rst
reslate_finesse/templates/templates/multiclass_header.rst
reslate_finesse/templates/templates/properties_section.rst
reslate_finesse/templates/templates/simplemod_header.rst
reslate_finesse/templates/templates/single_class_overview.rst
reslate_finesse/templates/templates/singleclass_header.rst
reslate_finesse/templates/templates/submodules_summaries.rst
reslate_finesse/templates/templates/subpkg_overview.rst
reslate_finesse-0.59.0.dist-info/licenses/LICENSE
reslate_finesse-0.59.0.dist-info/METADATA
reslate_finesse-0.59.0.dist-info/WHEEL
reslate_finesse-0.59.0.dist-info/entry_points.txt
reslate_finesse-0.59.0.dist-info/top_level.txt
reslate_finesse-0.59.0.dist-info/RECORD
